PythonFastCycles/__init__.py
PythonFastCycles/process_data.py
PythonFastCycles/simulation.py
PythonFastCycles/tools.py
src/__init__.py
src/process_data.py
src/simulation.py
src/tools.py
PythonFastCycles-1.0.11.dist-info/LICENSE
PythonFastCycles-1.0.11.dist-info/METADATA
PythonFastCycles-1.0.11.dist-info/WHEEL
PythonFastCycles-1.0.11.dist-info/top_level.txt
PythonFastCycles-1.0.11.dist-info/RECORD
