Metadata-Version: 2.1
Name: PythonFastCycles
Version: 1.0.11
Summary: Package to interact with FastCycles
Home-page: https://github.com/rferry/PythonFastCycles
Author: Roxane Ferry
Author-email: roxane.ferry@ens.fr
License: UNKNOWN
Keywords: fast cycles earthquake romanet
Platform: UNKNOWN
Classifier: Programming Language :: Python :: 3
Classifier: License :: OSI Approved :: GNU General Public License (GPL)
Classifier: Operating System :: OS Independent
Requires-Python: >=3.6
Requires-Dist: setuptools-git
